{"tags":[{"name":"Nuxt.js","slug":"nuxt-js","posts":["contents/blog/json/2020-01-hyan.json","contents/blog/json/2020-01-piyo.json","contents/blog/json/2020-01-hoge.json","contents/blog/json/2020-01-fugo.json","contents/blog/json/2020-01-pepe.json","contents/blog/json/2020-01-popo.json","contents/blog/json/2020-02-fugo.json"]},{"name":"jade","slug":"jade","posts":["contents/blog/json/2020-01-hyan.json","contents/blog/json/2020-01-piyo.json","contents/blog/json/2020-01-hoge.json","contents/blog/json/2020-01-fugo.json","contents/blog/json/2020-01-pepe.json","contents/blog/json/2020-01-popo.json","contents/blog/json/2020-02-fugo.json"]},{"name":"gulp","slug":"gulp","posts":["contents/blog/json/2020-01-hyan.json","contents/blog/json/2020-01-piyo.json","contents/blog/json/2020-01-hoge.json","contents/blog/json/2020-01-pepe.json","contents/blog/json/2020-01-popo.json","contents/blog/json/2020-02-fugo.json"]},{"name":"お神輿","slug":"omikoshi","posts":["contents/blog/json/2020-01-fugo.json"]}],"categories":[{"name":"tech","slug":"tech","posts":["contents/blog/json/2020-01-hyan.json","contents/blog/json/2020-01-piyo.json","contents/blog/json/2020-01-hoge.json","contents/blog/json/2020-01-fugo.json","contents/blog/json/2020-01-pepe.json","contents/blog/json/2020-01-popo.json"]},{"name":"hoge","slug":"hoge","posts":["contents/blog/json/2020-02-fugo.json"]}],"yearly":{"2020":["contents/blog/json/2020-01-hyan.json","contents/blog/json/2020-01-piyo.json","contents/blog/json/2020-01-hoge.json","contents/blog/json/2020-01-fugo.json","contents/blog/json/2020-01-pepe.json","contents/blog/json/2020-01-popo.json","contents/blog/json/2020-02-fugo.json"]},"monthly":{"2020":{"01":["contents/blog/json/2020-01-hyan.json","contents/blog/json/2020-01-piyo.json","contents/blog/json/2020-01-hoge.json","contents/blog/json/2020-01-fugo.json","contents/blog/json/2020-01-pepe.json","contents/blog/json/2020-01-popo.json"],"02":["contents/blog/json/2020-02-fugo.json"]}}}